ratransformers/__init__.py
ratransformers/bart.py
ratransformers/bert.py
ratransformers/gpt2.py
ratransformers/roberta.py
ratransformers/t5.py
ratransformers-0.1.1.dist-info/LICENSE
ratransformers-0.1.1.dist-info/METADATA
ratransformers-0.1.1.dist-info/WHEEL
ratransformers-0.1.1.dist-info/top_level.txt
ratransformers-0.1.1.dist-info/RECORD
