Metadata-Version: 2.1
Name: ratransformers
Version: 0.1.1
Summary: RATransformer - make a transformer model learn implicit relations passed in the input
Home-page: https://github.com/JoaoLages/RATransformers
Author: Joao Lages
Author-email: joaop.glages@gmail.com
License: MIT
Platform: UNKNOWN
License-File: LICENSE
Requires-Dist: numpy (>=1.19.1)
Requires-Dist: transformers (>=4.6.1)
Requires-Dist: setuptools (>=49.6.0)
Requires-Dist: pytest (>=7.0.1)
Requires-Dist: torch (>=1.9.1)
